edbo_connector/__init__.py
edbo_connector/client.py
edbo_connector/config.py
edbo_connector/connector.py
edbo_connector/helper.py
edbo_connector/methods.py
edbo_connector/tests/__init__.py
edbo_connector/tests/test_client.py
edbo_connector/tests/test_connector.py
edbo_connector/tests/test_helper.py
edbo_connector/tests/test_methods.py
python_edbo_connector-1.0.4.post13.dist-info/DESCRIPTION.rst
python_edbo_connector-1.0.4.post13.dist-info/LICENSE.txt
python_edbo_connector-1.0.4.post13.dist-info/METADATA
python_edbo_connector-1.0.4.post13.dist-info/RECORD
python_edbo_connector-1.0.4.post13.dist-info/WHEEL
python_edbo_connector-1.0.4.post13.dist-info/metadata.json
python_edbo_connector-1.0.4.post13.dist-info/top_level.txt
