Metadata-Version: 2.0
Name: python-edbo-connector
Version: 1.0.4.post13
Summary: Python connector for EDBO based on python-requests
Home-page: https://github.com/EldarAliiev/python-edbo-connector
Author: Eldar Aliiev
Author-email: e.aliiev@vnmu.edu.ua
Maintainer: Eldar Aliiev
Maintainer-email: e.aliiev@vnmu.edu.ua
License: MIT
Download-URL: https://github.com/EldarAliiev/python-edbo-connector/archive/master.zip
Keywords: EDBO,connector,RESTful API,EDBO client
Platform: UNKNOWN
Classifier: Development Status :: 5 - Production/Stable
Classifier: Natural Language :: English
Classifier: License :: OSI Approved :: MIT License
Classifier: Operating System :: OS Independent
Classifier: Intended Audience :: Developers
Classifier: Intended Audience :: System Administrators
Classifier: Programming Language :: Python :: 3
Classifier: Programming Language :: Python :: 3.4
Classifier: Programming Language :: Python :: 3.5
Classifier: Programming Language :: Python :: 3.6
Classifier: Topic :: Communications
Requires-Python: >=3.4
Requires-Dist: setuptools
